setup.py
pylice/__init__.py
pylice/main.py
pylice/pylice.py
pylice.egg-info/PKG-INFO
pylice.egg-info/SOURCES.txt
pylice.egg-info/dependency_links.txt
pylice.egg-info/entry_points.txt
pylice.egg-info/top_level.txt