Metadata-Version: 1.1
Name: pylice
Version: 0.1.0
Summary: Retrieves license information for installed Python packages.
Home-page: https://github.com/tjpnz/pylice
Author: Thomas Prebble
Author-email: thomas.prebble@gmail.com
License: MIT
Keywords: versioning
Platform: UNKNOWN
Classifier: Development Status :: 4 - Beta
Classifier: Intended Audience :: Developers
Classifier: Topic :: Software Development
Classifier: License :: OSI Approved :: MIT License
Classifier: Programming Language :: Python :: 2.6
Classifier: Programming Language :: Python :: 2.7
Classifier: Programming Language :: Python :: 3
